{"url":"https:\/\/edu-bmn.id\/index.php\/admin\/data\/peralatan-dan-mesin","method":"GET","isAJAX":false,"startTime":1664161338.852236,"totalTime":100.5,"totalMemory":"1.679","segmentDuration":15,"segmentCount":7,"CI_VERSION":"4.2.6","collectors":[{"title":"Timers","titleSafe":"timers","titleDetails":"","display":[],"badgeValue":null,"isEmpty":false,"hasTabContent":false,"hasLabel":false,"icon":"","hasTimelineData":true,"timelineData":[{"name":"Bootstrap","component":"Timer","start":1664161338.876703,"duration":0.027359962463378906},{"name":"Routing","component":"Timer","start":1664161338.904067,"duration":0.0002410411834716797},{"name":"Before Filters","component":"Timer","start":1664161338.906511,"duration":0.03053903579711914},{"name":"Controller","component":"Timer","start":1664161338.937062,"duration":0.01566004753112793},{"name":"Controller Constructor","component":"Timer","start":1664161338.937064,"duration":0.0027120113372802734},{"name":"After Filters","component":"Timer","start":1664161338.953945,"duration":0.0015020370483398438}]},{"title":"Database","titleSafe":"database","titleDetails":"(3 total Queries, 2 of them unique across 1 Connection)","display":{"queries":[{"hover":"","class":"","duration":"0.71 ms","sql":"<strong>SELECT<\/strong> *\n<strong>FROM<\/strong> `users`\n<strong>WHERE<\/strong> `email` = &#039;admin@edu-bmn.id&#039;\n<strong>AND<\/strong> `users`.`deleted_at` <strong>IS<\/strong> <strong>NULL<\/strong>","trace":[{"file":"SYSTEMPATH\/Database\/BaseBuilder.php:1585","function":"\u00a0\u00a0\u00a0\u00a0\u00a0\u00a0\u00a0\u00a0CodeIgniter\\Database\\BaseConnection->query()","index":"\u00a0\u00a01\u00a0\u00a0\u00a0\u00a0"},{"file":"SYSTEMPATH\/Model.php:185","function":"\u00a0\u00a0\u00a0\u00a0\u00a0\u00a0\u00a0\u00a0CodeIgniter\\Database\\BaseBuilder->get()","index":"\u00a0\u00a02\u00a0\u00a0\u00a0\u00a0"},{"file":"SYSTEMPATH\/BaseModel.php:523","function":"\u00a0\u00a0\u00a0\u00a0\u00a0\u00a0\u00a0\u00a0CodeIgniter\\Model->doFind()","index":"\u00a0\u00a03\u00a0\u00a0\u00a0\u00a0"},{"file":"APPPATH\/Filters\/Adminauth.php:39","function":"\u00a0\u00a0\u00a0\u00a0\u00a0\u00a0\u00a0\u00a0CodeIgniter\\BaseModel->find()","index":"\u00a0\u00a04\u00a0\u00a0\u00a0\u00a0"},{"file":"SYSTEMPATH\/Filters\/Filters.php:173","function":"\u00a0\u00a0\u00a0\u00a0\u00a0\u00a0\u00a0\u00a0App\\Filters\\Adminauth->before()","index":"\u00a0\u00a05\u00a0\u00a0\u00a0\u00a0"},{"file":"SYSTEMPATH\/CodeIgniter.php:431","function":"\u00a0\u00a0\u00a0\u00a0\u00a0\u00a0\u00a0\u00a0CodeIgniter\\Filters\\Filters->run()","index":"\u00a0\u00a06\u00a0\u00a0\u00a0\u00a0"},{"file":"SYSTEMPATH\/CodeIgniter.php:340","function":"\u00a0\u00a0\u00a0\u00a0\u00a0\u00a0\u00a0\u00a0CodeIgniter\\CodeIgniter->handleRequest()","index":"\u00a0\u00a07\u00a0\u00a0\u00a0\u00a0"},{"file":"FCPATH\/index.php:67","function":"\u00a0\u00a0\u00a0\u00a0\u00a0\u00a0\u00a0\u00a0CodeIgniter\\CodeIgniter->run()","index":"\u00a0\u00a08\u00a0\u00a0\u00a0\u00a0"}],"trace-file":"APPPATH\/Filters\/Adminauth.php:39","qid":"1fa9d2d13e0d5c88562648dd91d5814b"},{"hover":"This query was called more than once.","class":"duplicate","duration":"1.01 ms","sql":"<strong>SELECT<\/strong> *\n<strong>FROM<\/strong> `users`\n<strong>WHERE<\/strong> `email` = &#039;admin@edu-bmn.id&#039;\n<strong>AND<\/strong> `users`.`deleted_at` <strong>IS<\/strong> <strong>NULL<\/strong>","trace":[{"file":"SYSTEMPATH\/Database\/BaseBuilder.php:1585","function":"\u00a0\u00a0\u00a0\u00a0\u00a0\u00a0\u00a0\u00a0CodeIgniter\\Database\\BaseConnection->query()","index":"\u00a0\u00a01\u00a0\u00a0\u00a0\u00a0"},{"file":"SYSTEMPATH\/Model.php:223","function":"\u00a0\u00a0\u00a0\u00a0\u00a0\u00a0\u00a0\u00a0CodeIgniter\\Database\\BaseBuilder->get()","index":"\u00a0\u00a02\u00a0\u00a0\u00a0\u00a0"},{"file":"SYSTEMPATH\/BaseModel.php:584","function":"\u00a0\u00a0\u00a0\u00a0\u00a0\u00a0\u00a0\u00a0CodeIgniter\\Model->doFindAll()","index":"\u00a0\u00a03\u00a0\u00a0\u00a0\u00a0"},{"file":"APPPATH\/Controllers\/Admin.php:173","function":"\u00a0\u00a0\u00a0\u00a0\u00a0\u00a0\u00a0\u00a0CodeIgniter\\BaseModel->findAll()","index":"\u00a0\u00a04\u00a0\u00a0\u00a0\u00a0"},{"file":"SYSTEMPATH\/CodeIgniter.php:907","function":"\u00a0\u00a0\u00a0\u00a0\u00a0\u00a0\u00a0\u00a0App\\Controllers\\Admin->pdmdata()","index":"\u00a0\u00a05\u00a0\u00a0\u00a0\u00a0"},{"file":"SYSTEMPATH\/CodeIgniter.php:457","function":"\u00a0\u00a0\u00a0\u00a0\u00a0\u00a0\u00a0\u00a0CodeIgniter\\CodeIgniter->runController()","index":"\u00a0\u00a06\u00a0\u00a0\u00a0\u00a0"},{"file":"SYSTEMPATH\/CodeIgniter.php:340","function":"\u00a0\u00a0\u00a0\u00a0\u00a0\u00a0\u00a0\u00a0CodeIgniter\\CodeIgniter->handleRequest()","index":"\u00a0\u00a07\u00a0\u00a0\u00a0\u00a0"},{"file":"FCPATH\/index.php:67","function":"\u00a0\u00a0\u00a0\u00a0\u00a0\u00a0\u00a0\u00a0CodeIgniter\\CodeIgniter->run()","index":"\u00a0\u00a08\u00a0\u00a0\u00a0\u00a0"}],"trace-file":"APPPATH\/Controllers\/Admin.php:173","qid":"e5684e5b90f66491dd5f6392327c58a3"},{"hover":"","class":"","duration":"3.05 ms","sql":"<strong>SELECT<\/strong> *\n<strong>FROM<\/strong> `pdms`\n<strong>WHERE<\/strong> `pdms`.`deleted_at` <strong>IS<\/strong> <strong>NULL<\/strong>","trace":[{"file":"SYSTEMPATH\/Database\/BaseBuilder.php:1585","function":"\u00a0\u00a0\u00a0\u00a0\u00a0\u00a0\u00a0\u00a0CodeIgniter\\Database\\BaseConnection->query()","index":"\u00a0\u00a01\u00a0\u00a0\u00a0\u00a0"},{"file":"SYSTEMPATH\/Model.php:223","function":"\u00a0\u00a0\u00a0\u00a0\u00a0\u00a0\u00a0\u00a0CodeIgniter\\Database\\BaseBuilder->get()","index":"\u00a0\u00a02\u00a0\u00a0\u00a0\u00a0"},{"file":"SYSTEMPATH\/BaseModel.php:584","function":"\u00a0\u00a0\u00a0\u00a0\u00a0\u00a0\u00a0\u00a0CodeIgniter\\Model->doFindAll()","index":"\u00a0\u00a03\u00a0\u00a0\u00a0\u00a0"},{"file":"APPPATH\/Controllers\/Admin.php:174","function":"\u00a0\u00a0\u00a0\u00a0\u00a0\u00a0\u00a0\u00a0CodeIgniter\\BaseModel->findAll()","index":"\u00a0\u00a04\u00a0\u00a0\u00a0\u00a0"},{"file":"SYSTEMPATH\/CodeIgniter.php:907","function":"\u00a0\u00a0\u00a0\u00a0\u00a0\u00a0\u00a0\u00a0App\\Controllers\\Admin->pdmdata()","index":"\u00a0\u00a05\u00a0\u00a0\u00a0\u00a0"},{"file":"SYSTEMPATH\/CodeIgniter.php:457","function":"\u00a0\u00a0\u00a0\u00a0\u00a0\u00a0\u00a0\u00a0CodeIgniter\\CodeIgniter->runController()","index":"\u00a0\u00a06\u00a0\u00a0\u00a0\u00a0"},{"file":"SYSTEMPATH\/CodeIgniter.php:340","function":"\u00a0\u00a0\u00a0\u00a0\u00a0\u00a0\u00a0\u00a0CodeIgniter\\CodeIgniter->handleRequest()","index":"\u00a0\u00a07\u00a0\u00a0\u00a0\u00a0"},{"file":"FCPATH\/index.php:67","function":"\u00a0\u00a0\u00a0\u00a0\u00a0\u00a0\u00a0\u00a0CodeIgniter\\CodeIgniter->run()","index":"\u00a0\u00a08\u00a0\u00a0\u00a0\u00a0"}],"trace-file":"APPPATH\/Controllers\/Admin.php:174","qid":"2a39c6c762771d9b3ded4a62623229a2"}]},"badgeValue":3,"isEmpty":false,"hasTabContent":true,"hasLabel":false,"icon":"data:image\/png;base64,iVBORw0KGgoAAAANSUhEUgAAABgAAAAYCAYAAADgdz34AAAAAXNSR0IArs4c6QAAAARnQU1BAACxjwv8YQUAAAAJcEhZcwAADsMAAA7DAcdvqGQAAADMSURBVEhLY6A3YExLSwsA4nIycQDIDIhRWEBqamo\/UNF\/SjDQjF6ocZgAKPkRiFeEhoYyQ4WIBiA9QAuWAPEHqBAmgLqgHcolGQD1V4DMgHIxwbCxYD+QBqcKINseKo6eWrBioPrtQBq\/BcgY5ht0cUIYbBg2AJKkRxCNWkDQgtFUNJwtABr+F6igE8olGQD114HMgHIxAVDyAhA\/AlpSA8RYUwoeXAPVex5qHCbIyMgwBCkAuQJIY00huDBUz\/mUlBQDqHGjgBjAwAAACexpph6oHSQAAAAASUVORK5CYII=","hasTimelineData":true,"timelineData":[{"name":"Connecting to Database: \"default\"","component":"Database","start":1664161338.929746,"duration":"0.005165"},{"name":"Query","component":"Database","start":1664161338.93538,"duration":"0.000706","query":"<strong>SELECT<\/strong> *\n<strong>FROM<\/strong> `users`\n<strong>WHERE<\/strong> `email` = &#039;admin@edu-bmn.id&#039;\n<strong>AND<\/strong> `users`.`deleted_at` <strong>IS<\/strong> <strong>NULL<\/strong>"},{"name":"Query","component":"Database","start":1664161338.939982,"duration":"0.001010","query":"<strong>SELECT<\/strong> *\n<strong>FROM<\/strong> `users`\n<strong>WHERE<\/strong> `email` = &#039;admin@edu-bmn.id&#039;\n<strong>AND<\/strong> `users`.`deleted_at` <strong>IS<\/strong> <strong>NULL<\/strong>"},{"name":"Query","component":"Database","start":1664161338.941217,"duration":"0.003045","query":"<strong>SELECT<\/strong> *\n<strong>FROM<\/strong> `pdms`\n<strong>WHERE<\/strong> `pdms`.`deleted_at` <strong>IS<\/strong> <strong>NULL<\/strong>"}]},{"title":"Logs","titleSafe":"logs","titleDetails":"","display":{"logs":[]},"badgeValue":null,"isEmpty":true,"hasTabContent":true,"hasLabel":false,"icon":"data:image\/png;base64,iVBORw0KGgoAAAANSUhEUgAAABgAAAAYCAYAAADgdz34AAAAAXNSR0IArs4c6QAAAARnQU1BAACxjwv8YQUAAAAJcEhZcwAADsMAAA7DAcdvqGQAAACYSURBVEhLYxgFJIHU1FSjtLS0i0D8AYj7gEKMEBkqAaAFF4D4ERCvAFrwH4gDoFIMKSkpFkB+OTEYqgUTACXfA\/GqjIwMQyD9H2hRHlQKJFcBEiMGQ7VgAqCBvUgK32dmZspCpagGGNPT0\/1BLqeF4bQHQJePpiIwhmrBBEADR1MRfgB0+WgqAmOoFkwANHA0FY0CUgEDAwCQ0PUpNB3kqwAAAABJRU5ErkJggg==","hasTimelineData":false,"timelineData":[]},{"title":"Views","titleSafe":"views","titleDetails":"","display":[],"badgeValue":5,"isEmpty":false,"hasTabContent":false,"hasLabel":true,"icon":"data:image\/png;base64,iVBORw0KGgoAAAANSUhEUgAAABgAAAAYCAYAAADgdz34AAAAAXNSR0IArs4c6QAAAARnQU1BAACxjwv8YQUAAAAJcEhZcwAADsMAAA7DAcdvqGQAAADeSURBVEhL7ZSxDcIwEEWNYA0YgGmgyAaJLTcUaaBzQQEVjMEabBQxAdw53zTHiThEovGTfnE\/9rsoRUxhKLOmaa6Uh7X2+UvguLCzVxN1XW9x4EYHzik033Hp3X0LO+DaQG8MDQcuq6qao4qkHuMgQggLvkPLjqh00ZgFDBacMJYFkuwFlH1mshdkZ5JPJERA9JpI6xNCBESvibQ+IURA9JpI6xNCBESvibQ+IURA9DTsuHTOrVFFxixgB\/eUFlU8uKJ0eDBFOu\/9EvoeKnlJS2\/08Tc8NOwQ8sIfMeYFjqKDjdU2sp4AAAAASUVORK5CYII=","hasTimelineData":true,"timelineData":[{"name":"View: admin\/components\/links.php","component":"Views","start":1664161338.947116,"duration":0.0005061626434326172},{"name":"View: admin\/components\/sidebar.php","component":"Views","start":1664161338.94771,"duration":0.0003230571746826172},{"name":"View: admin\/components\/topbar.php","component":"Views","start":1664161338.948075,"duration":0.003947019577026367},{"name":"View: admin\/components\/scripts.php","component":"Views","start":1664161338.952155,"duration":0.000415802001953125},{"name":"View: admin\/pdm.php","component":"Views","start":1664161338.944571,"duration":0.008085012435913086}]},{"title":"Files","titleSafe":"files","titleDetails":"( 140 )","display":{"coreFiles":[{"name":"AutoloadConfig.php","path":"SYSTEMPATH\/Config\/AutoloadConfig.php"},{"name":"Autoloader.php","path":"SYSTEMPATH\/Autoloader\/Autoloader.php"},{"name":"BaseBuilder.php","path":"SYSTEMPATH\/Database\/BaseBuilder.php"},{"name":"BaseCollector.php","path":"SYSTEMPATH\/Debug\/Toolbar\/Collectors\/BaseCollector.php"},{"name":"BaseConfig.php","path":"SYSTEMPATH\/Config\/BaseConfig.php"},{"name":"BaseConnection.php","path":"SYSTEMPATH\/Database\/BaseConnection.php"},{"name":"BaseHandler.php","path":"SYSTEMPATH\/Cache\/Handlers\/BaseHandler.php"},{"name":"BaseHandler.php","path":"SYSTEMPATH\/Session\/Handlers\/BaseHandler.php"},{"name":"BaseModel.php","path":"SYSTEMPATH\/BaseModel.php"},{"name":"BaseResult.php","path":"SYSTEMPATH\/Database\/BaseResult.php"},{"name":"BaseService.php","path":"SYSTEMPATH\/Config\/BaseService.php"},{"name":"Builder.php","path":"SYSTEMPATH\/Database\/MySQLi\/Builder.php"},{"name":"CacheFactory.php","path":"SYSTEMPATH\/Cache\/CacheFactory.php"},{"name":"CacheInterface.php","path":"SYSTEMPATH\/Cache\/CacheInterface.php"},{"name":"CloneableCookieInterface.php","path":"SYSTEMPATH\/Cookie\/CloneableCookieInterface.php"},{"name":"CodeIgniter.php","path":"SYSTEMPATH\/CodeIgniter.php"},{"name":"Common.php","path":"SYSTEMPATH\/Common.php"},{"name":"Config.php","path":"SYSTEMPATH\/Database\/Config.php"},{"name":"Connection.php","path":"SYSTEMPATH\/Database\/MySQLi\/Connection.php"},{"name":"ConnectionInterface.php","path":"SYSTEMPATH\/Database\/ConnectionInterface.php"},{"name":"ContentSecurityPolicy.php","path":"SYSTEMPATH\/HTTP\/ContentSecurityPolicy.php"},{"name":"Controller.php","path":"SYSTEMPATH\/Controller.php"},{"name":"Cookie.php","path":"SYSTEMPATH\/Cookie\/Cookie.php"},{"name":"CookieInterface.php","path":"SYSTEMPATH\/Cookie\/CookieInterface.php"},{"name":"CookieStore.php","path":"SYSTEMPATH\/Cookie\/CookieStore.php"},{"name":"Database.php","path":"SYSTEMPATH\/Database\/Database.php"},{"name":"Database.php","path":"SYSTEMPATH\/Debug\/Toolbar\/Collectors\/Database.php"},{"name":"DebugToolbar.php","path":"SYSTEMPATH\/Filters\/DebugToolbar.php"},{"name":"DotEnv.php","path":"SYSTEMPATH\/Config\/DotEnv.php"},{"name":"Escaper.php","path":"SYSTEMPATH\/ThirdParty\/Escaper\/Escaper.php"},{"name":"Events.php","path":"SYSTEMPATH\/Debug\/Toolbar\/Collectors\/Events.php"},{"name":"Events.php","path":"SYSTEMPATH\/Events\/Events.php"},{"name":"Exceptions.php","path":"SYSTEMPATH\/Debug\/Exceptions.php"},{"name":"Factories.php","path":"SYSTEMPATH\/Config\/Factories.php"},{"name":"Factory.php","path":"SYSTEMPATH\/Config\/Factory.php"},{"name":"FileHandler.php","path":"SYSTEMPATH\/Cache\/Handlers\/FileHandler.php"},{"name":"FileHandler.php","path":"SYSTEMPATH\/Session\/Handlers\/FileHandler.php"},{"name":"FileLocator.php","path":"SYSTEMPATH\/Autoloader\/FileLocator.php"},{"name":"Files.php","path":"SYSTEMPATH\/Debug\/Toolbar\/Collectors\/Files.php"},{"name":"FilterInterface.php","path":"SYSTEMPATH\/Filters\/FilterInterface.php"},{"name":"Filters.php","path":"SYSTEMPATH\/Filters\/Filters.php"},{"name":"FormatRules.php","path":"SYSTEMPATH\/Validation\/FormatRules.php"},{"name":"Header.php","path":"SYSTEMPATH\/HTTP\/Header.php"},{"name":"IncomingRequest.php","path":"SYSTEMPATH\/HTTP\/IncomingRequest.php"},{"name":"Logger.php","path":"SYSTEMPATH\/Log\/Logger.php"},{"name":"LoggerAwareTrait.php","path":"SYSTEMPATH\/ThirdParty\/PSR\/Log\/LoggerAwareTrait.php"},{"name":"LoggerInterface.php","path":"SYSTEMPATH\/ThirdParty\/PSR\/Log\/LoggerInterface.php"},{"name":"Logs.php","path":"SYSTEMPATH\/Debug\/Toolbar\/Collectors\/Logs.php"},{"name":"Message.php","path":"SYSTEMPATH\/HTTP\/Message.php"},{"name":"MessageInterface.php","path":"SYSTEMPATH\/HTTP\/MessageInterface.php"},{"name":"MessageTrait.php","path":"SYSTEMPATH\/HTTP\/MessageTrait.php"},{"name":"Model.php","path":"SYSTEMPATH\/Model.php"},{"name":"Modules.php","path":"SYSTEMPATH\/Modules\/Modules.php"},{"name":"Query.php","path":"SYSTEMPATH\/Database\/Query.php"},{"name":"QueryInterface.php","path":"SYSTEMPATH\/Database\/QueryInterface.php"},{"name":"RendererInterface.php","path":"SYSTEMPATH\/View\/RendererInterface.php"},{"name":"Request.php","path":"SYSTEMPATH\/HTTP\/Request.php"},{"name":"RequestInterface.php","path":"SYSTEMPATH\/HTTP\/RequestInterface.php"},{"name":"RequestTrait.php","path":"SYSTEMPATH\/HTTP\/RequestTrait.php"},{"name":"Response.php","path":"SYSTEMPATH\/HTTP\/Response.php"},{"name":"ResponseInterface.php","path":"SYSTEMPATH\/HTTP\/ResponseInterface.php"},{"name":"ResponseTrait.php","path":"SYSTEMPATH\/API\/ResponseTrait.php"},{"name":"ResponseTrait.php","path":"SYSTEMPATH\/HTTP\/ResponseTrait.php"},{"name":"Result.php","path":"SYSTEMPATH\/Database\/MySQLi\/Result.php"},{"name":"ResultInterface.php","path":"SYSTEMPATH\/Database\/ResultInterface.php"},{"name":"RouteCollection.php","path":"SYSTEMPATH\/Router\/RouteCollection.php"},{"name":"RouteCollectionInterface.php","path":"SYSTEMPATH\/Router\/RouteCollectionInterface.php"},{"name":"Router.php","path":"SYSTEMPATH\/Router\/Router.php"},{"name":"RouterInterface.php","path":"SYSTEMPATH\/Router\/RouterInterface.php"},{"name":"Routes.php","path":"SYSTEMPATH\/Config\/Routes.php"},{"name":"Routes.php","path":"SYSTEMPATH\/Debug\/Toolbar\/Collectors\/Routes.php"},{"name":"Services.php","path":"SYSTEMPATH\/Config\/Services.php"},{"name":"Session.php","path":"SYSTEMPATH\/Session\/Session.php"},{"name":"SessionInterface.php","path":"SYSTEMPATH\/Session\/SessionInterface.php"},{"name":"Timer.php","path":"SYSTEMPATH\/Debug\/Timer.php"},{"name":"Timers.php","path":"SYSTEMPATH\/Debug\/Toolbar\/Collectors\/Timers.php"},{"name":"Toolbar.php","path":"SYSTEMPATH\/Debug\/Toolbar.php"},{"name":"URI.php","path":"SYSTEMPATH\/HTTP\/URI.php"},{"name":"UserAgent.php","path":"SYSTEMPATH\/HTTP\/UserAgent.php"},{"name":"Validation.php","path":"SYSTEMPATH\/Validation\/Validation.php"},{"name":"ValidationInterface.php","path":"SYSTEMPATH\/Validation\/ValidationInterface.php"},{"name":"View.php","path":"SYSTEMPATH\/Config\/View.php"},{"name":"View.php","path":"SYSTEMPATH\/View\/View.php"},{"name":"ViewDecoratorTrait.php","path":"SYSTEMPATH\/View\/ViewDecoratorTrait.php"},{"name":"Views.php","path":"SYSTEMPATH\/Debug\/Toolbar\/Collectors\/Views.php"},{"name":"array_helper.php","path":"SYSTEMPATH\/Helpers\/array_helper.php"},{"name":"bootstrap.php","path":"SYSTEMPATH\/bootstrap.php"},{"name":"url_helper.php","path":"SYSTEMPATH\/Helpers\/url_helper.php"}],"userFiles":[{"name":"Admin.php","path":"APPPATH\/Controllers\/Admin.php"},{"name":"Adminauth.php","path":"APPPATH\/Filters\/Adminauth.php"},{"name":"App.php","path":"APPPATH\/Config\/App.php"},{"name":"AtlModel.php","path":"APPPATH\/Models\/AtlModel.php"},{"name":"Autoload.php","path":"APPPATH\/Config\/Autoload.php"},{"name":"BaseController.php","path":"APPPATH\/Controllers\/BaseController.php"},{"name":"Cache.php","path":"APPPATH\/Config\/Cache.php"},{"name":"ClassLoader.php","path":"FCPATH\/vendor\/composer\/ClassLoader.php"},{"name":"CliRenderer.php","path":"FCPATH\/vendor\/kint-php\/kint\/src\/Renderer\/CliRenderer.php"},{"name":"Common.php","path":"APPPATH\/Common.php"},{"name":"Constants.php","path":"APPPATH\/Config\/Constants.php"},{"name":"ContentSecurityPolicy.php","path":"APPPATH\/Config\/ContentSecurityPolicy.php"},{"name":"Cookie.php","path":"APPPATH\/Config\/Cookie.php"},{"name":"Database.php","path":"APPPATH\/Config\/Database.php"},{"name":"Events.php","path":"APPPATH\/Config\/Events.php"},{"name":"Exceptions.php","path":"APPPATH\/Config\/Exceptions.php"},{"name":"Feature.php","path":"APPPATH\/Config\/Feature.php"},{"name":"Filters.php","path":"APPPATH\/Config\/Filters.php"},{"name":"GdbModel.php","path":"APPPATH\/Models\/GdbModel.php"},{"name":"JijModel.php","path":"APPPATH\/Models\/JijModel.php"},{"name":"KdpModel.php","path":"APPPATH\/Models\/KdpModel.php"},{"name":"Kint.php","path":"APPPATH\/Config\/Kint.php"},{"name":"Kint.php","path":"FCPATH\/vendor\/kint-php\/kint\/src\/Kint.php"},{"name":"Logger.php","path":"APPPATH\/Config\/Logger.php"},{"name":"Modules.php","path":"APPPATH\/Config\/Modules.php"},{"name":"Paths.php","path":"APPPATH\/Config\/Paths.php"},{"name":"PdmModel.php","path":"APPPATH\/Models\/PdmModel.php"},{"name":"Renderer.php","path":"FCPATH\/vendor\/kint-php\/kint\/src\/Renderer\/Renderer.php"},{"name":"RichRenderer.php","path":"FCPATH\/vendor\/kint-php\/kint\/src\/Renderer\/RichRenderer.php"},{"name":"Routes.php","path":"APPPATH\/Config\/Routes.php"},{"name":"Services.php","path":"APPPATH\/Config\/Services.php"},{"name":"TextRenderer.php","path":"FCPATH\/vendor\/kint-php\/kint\/src\/Renderer\/TextRenderer.php"},{"name":"TnhModel.php","path":"APPPATH\/Models\/TnhModel.php"},{"name":"Toolbar.php","path":"APPPATH\/Config\/Toolbar.php"},{"name":"UserAgents.php","path":"APPPATH\/Config\/UserAgents.php"},{"name":"UserModel.php","path":"APPPATH\/Models\/UserModel.php"},{"name":"Utils.php","path":"FCPATH\/vendor\/kint-php\/kint\/src\/Utils.php"},{"name":"Validation.php","path":"APPPATH\/Config\/Validation.php"},{"name":"View.php","path":"APPPATH\/Config\/View.php"},{"name":"autoload.php","path":"FCPATH\/vendor\/autoload.php"},{"name":"autoload_real.php","path":"FCPATH\/vendor\/composer\/autoload_real.php"},{"name":"autoload_static.php","path":"FCPATH\/vendor\/composer\/autoload_static.php"},{"name":"development.php","path":"APPPATH\/Config\/Boot\/development.php"},{"name":"index.php","path":"FCPATH\/index.php"},{"name":"init.php","path":"FCPATH\/vendor\/kint-php\/kint\/init.php"},{"name":"init_helpers.php","path":"FCPATH\/vendor\/kint-php\/kint\/init_helpers.php"},{"name":"links.php","path":"APPPATH\/Views\/admin\/components\/links.php"},{"name":"pdm.php","path":"APPPATH\/Views\/admin\/pdm.php"},{"name":"platform_check.php","path":"FCPATH\/vendor\/composer\/platform_check.php"},{"name":"scripts.php","path":"APPPATH\/Views\/admin\/components\/scripts.php"},{"name":"sidebar.php","path":"APPPATH\/Views\/admin\/components\/sidebar.php"},{"name":"topbar.php","path":"APPPATH\/Views\/admin\/components\/topbar.php"}]},"badgeValue":140,"isEmpty":false,"hasTabContent":true,"hasLabel":false,"icon":"data:image\/png;base64,iVBORw0KGgoAAAANSUhEUgAAABgAAAAYCAYAAADgdz34AAAAAXNSR0IArs4c6QAAAARnQU1BAACxjwv8YQUAAAAJcEhZcwAADsMAAA7DAcdvqGQAAAGBSURBVEhL7ZQ9S8NQGIVTBQUncfMfCO4uLgoKbuKQOWg+OkXERRE1IAXrIHbVDrqIDuLiJgj+gro7S3dnpfq88b1FMTE3VZx64HBzzvvZWxKnj15QCcPwCD5HUfSWR+JtzgmtsUcQBEva5IIm9SwSu+95CAWbUuy67qBa32ByZEDpIaZYZSZMjjQuPcQUq8yEyYEb8FSerYeQVGbAFzJkX1PyQWLhgCz0BxTCekC1Wp0hsa6yokzhed4oje6Iz6rlJEkyIKfUEFtITVtQdAibn5rMyaYsMS+a5wTv8qeXMhcU16QZbKgl3hbs+L4\/pnpdc87MElZgq10p5DxGdq8I7xrvUWUKvG3NbSK7ubngYzdJwSsF7TiOh9VOgfcEz1UayNe3JUPM1RWC5GXYgTfc75B4NBmXJnAtTfpABX0iPvEd9ezALwkplCFXcr9styiNOKc1RRZpaPM9tcqBwlWzGY1qPL9wjqRBgF5BH6j8HWh2S7MHlX8PrmbK+k\/8PzjOOzx1D3i1pKTTAAAAAElFTkSuQmCC","hasTimelineData":false,"timelineData":[]},{"title":"Routes","titleSafe":"routes","titleDetails":"","display":{"matchedRoute":[{"directory":"","controller":"\\App\\Controllers\\Admin","method":"pdmdata","paramCount":0,"truePCount":0,"params":[]}],"routes":[{"method":"GET","route":"\/","handler":"\\App\\Controllers\\Auth::login"},{"method":"GET","route":"login","handler":"\\App\\Controllers\\Auth::login"},{"method":"GET","route":"logout","handler":"\\App\\Controllers\\Auth::logout"},{"method":"GET","route":"admin","handler":"\\App\\Controllers\\Admin::index"},{"method":"GET","route":"admin\/user-management","handler":"\\App\\Controllers\\Admin::usermanagement"},{"method":"GET","route":"admin\/data\/peralatan-dan-mesin","handler":"\\App\\Controllers\\Admin::pdmdata"},{"method":"GET","route":"admin\/data\/tanah","handler":"\\App\\Controllers\\Admin::tnhdata"},{"method":"GET","route":"admin\/data\/gedung-dan-bangunan","handler":"\\App\\Controllers\\Admin::gdbdata"},{"method":"GET","route":"admin\/data\/jalan-irigasi-dan-jaringan","handler":"\\App\\Controllers\\Admin::jijdata"},{"method":"GET","route":"admin\/data\/aset-tetap-lainnya","handler":"\\App\\Controllers\\Admin::atldata"},{"method":"GET","route":"admin\/data\/konstruksi-dalam-pengerjaan","handler":"\\App\\Controllers\\Admin::kdpdata"},{"method":"GET","route":"pdm","handler":"\\App\\Controllers\\Pdm::index"},{"method":"GET","route":"pdm\/data\/peralatan-dan-mesin","handler":"\\App\\Controllers\\Pdm::pdmdata"},{"method":"GET","route":"tnh","handler":"\\App\\Controllers\\Tnh::index"},{"method":"GET","route":"tnh\/data\/tanah","handler":"\\App\\Controllers\\Tnh::tnhdata"},{"method":"GET","route":"gdb","handler":"\\App\\Controllers\\Gdb::index"},{"method":"GET","route":"gdb\/data\/gedung-dan-bangunan","handler":"\\App\\Controllers\\Gdb::gdbdata"},{"method":"GET","route":"jij","handler":"\\App\\Controllers\\Jij::index"},{"method":"GET","route":"jij\/data\/jalan-irigasi-dan-jaringan","handler":"\\App\\Controllers\\Jij::jijdata"},{"method":"GET","route":"atl","handler":"\\App\\Controllers\\Atl::index"},{"method":"GET","route":"atl\/data\/aset-tetap-lainnya","handler":"\\App\\Controllers\\Atl::atldata"},{"method":"GET","route":"kdp","handler":"\\App\\Controllers\\Kdp::index"},{"method":"GET","route":"kdp\/data\/konstruksi-dalam-pengerjaan","handler":"\\App\\Controllers\\Kdp::kdpdata"},{"method":"GET","route":"data\/pdm","handler":"\\App\\Controllers\\Home::pdmdata"},{"method":"POST","route":"login","handler":"\\App\\Controllers\\Auth::authenticate"},{"method":"POST","route":"admin\/user-management\/add","handler":"\\App\\Controllers\\Admin::adduser"},{"method":"POST","route":"admin\/user-management\/update","handler":"\\App\\Controllers\\Admin::edituser"},{"method":"POST","route":"admin\/user-management\/reset-password","handler":"\\App\\Controllers\\Admin::resetpassuser"},{"method":"POST","route":"admin\/user-management\/delete","handler":"\\App\\Controllers\\Admin::deleteuser"},{"method":"POST","route":"admin\/account\/update\/password","handler":"\\App\\Controllers\\Admin::updatepassword"},{"method":"POST","route":"admin\/account\/update\/email","handler":"\\App\\Controllers\\Admin::updateemail"},{"method":"POST","route":"admin\/data\/peralatan-dan-mesin\/upload","handler":"\\App\\Controllers\\Admin::pdmupload"},{"method":"POST","route":"admin\/data\/peralatan-dan-mesin\/detail","handler":"\\App\\Controllers\\Admin::pdmdetail"},{"method":"POST","route":"admin\/data\/peralatan-dan-mesin\/delete","handler":"\\App\\Controllers\\Admin::pdmdelete"},{"method":"POST","route":"admin\/data\/tanah\/upload","handler":"\\App\\Controllers\\Admin::tnhupload"},{"method":"POST","route":"admin\/data\/tanah\/detail","handler":"\\App\\Controllers\\Admin::tnhdetail"},{"method":"POST","route":"admin\/data\/tanah\/delete","handler":"\\App\\Controllers\\Admin::tnhdelete"},{"method":"POST","route":"admin\/data\/gedung-dan-bangunan\/upload","handler":"\\App\\Controllers\\Admin::gdbupload"},{"method":"POST","route":"admin\/data\/gedung-dan-bangunan\/detail","handler":"\\App\\Controllers\\Admin::gdbdetail"},{"method":"POST","route":"admin\/data\/gedung-dan-bangunan\/delete","handler":"\\App\\Controllers\\Admin::gdbdelete"},{"method":"POST","route":"admin\/data\/jalan-irigasi-dan-jaringan\/upload","handler":"\\App\\Controllers\\Admin::jijupload"},{"method":"POST","route":"admin\/data\/jalan-irigasi-dan-jaringan\/detail","handler":"\\App\\Controllers\\Admin::jijdetail"},{"method":"POST","route":"admin\/data\/jalan-irigasi-dan-jaringan\/delete","handler":"\\App\\Controllers\\Admin::jijdelete"},{"method":"POST","route":"admin\/data\/aset-tetap-lainnya\/upload","handler":"\\App\\Controllers\\Admin::atlupload"},{"method":"POST","route":"admin\/data\/aset-tetap-lainnya\/detail","handler":"\\App\\Controllers\\Admin::atldetail"},{"method":"POST","route":"admin\/data\/aset-tetap-lainnya\/delete","handler":"\\App\\Controllers\\Admin::atldelete"},{"method":"POST","route":"admin\/data\/konstruksi-dalam-pengerjaan\/upload","handler":"\\App\\Controllers\\Admin::kdpupload"},{"method":"POST","route":"admin\/data\/konstruksi-dalam-pengerjaan\/detail","handler":"\\App\\Controllers\\Admin::kdpdetail"},{"method":"POST","route":"admin\/data\/konstruksi-dalam-pengerjaan\/delete","handler":"\\App\\Controllers\\Admin::kdpdelete"},{"method":"POST","route":"pdm\/data\/peralatan-dan-mesin\/upload","handler":"\\App\\Controllers\\Pdm::pdmupload"},{"method":"POST","route":"pdm\/data\/peralatan-dan-mesin\/detail","handler":"\\App\\Controllers\\Pdm::pdmdetail"},{"method":"POST","route":"pdm\/data\/peralatan-dan-mesin\/delete","handler":"\\App\\Controllers\\Pdm::pdmdelete"},{"method":"POST","route":"pdm\/account\/update\/password","handler":"\\App\\Controllers\\Pdm::updatepassword"},{"method":"POST","route":"pdm\/account\/update\/email","handler":"\\App\\Controllers\\Pdm::updateemail"},{"method":"POST","route":"tnh\/data\/tanah\/upload","handler":"\\App\\Controllers\\Tnh::tnhupload"},{"method":"POST","route":"tnh\/data\/tanah\/detail","handler":"\\App\\Controllers\\Tnh::tnhdetail"},{"method":"POST","route":"tnh\/data\/tanah\/delete","handler":"\\App\\Controllers\\Tnh::tnhdelete"},{"method":"POST","route":"tnh\/account\/update\/password","handler":"\\App\\Controllers\\Tnh::updatepassword"},{"method":"POST","route":"tnh\/account\/update\/email","handler":"\\App\\Controllers\\Tnh::updateemail"},{"method":"POST","route":"gdb\/data\/gedung-dan-bangunan\/upload","handler":"\\App\\Controllers\\Gdb::gdbupload"},{"method":"POST","route":"gdb\/data\/gedung-dan-bangunan\/detail","handler":"\\App\\Controllers\\Gdb::gdbdetail"},{"method":"POST","route":"gdb\/data\/gedung-dan-bangunan\/delete","handler":"\\App\\Controllers\\Gdb::gdbdelete"},{"method":"POST","route":"gdb\/account\/update\/password","handler":"\\App\\Controllers\\Gdb::updatepassword"},{"method":"POST","route":"gdb\/account\/update\/email","handler":"\\App\\Controllers\\Gdb::updateemail"},{"method":"POST","route":"jij\/data\/jalan-irigasi-dan-jaringan\/upload","handler":"\\App\\Controllers\\Jij::jijupload"},{"method":"POST","route":"jij\/data\/jalan-irigasi-dan-jaringan\/detail","handler":"\\App\\Controllers\\Jij::jijdetail"},{"method":"POST","route":"jij\/data\/jalan-irigasi-dan-jaringan\/delete","handler":"\\App\\Controllers\\Jij::jijdelete"},{"method":"POST","route":"jij\/account\/update\/password","handler":"\\App\\Controllers\\Jij::updatepassword"},{"method":"POST","route":"jij\/account\/update\/email","handler":"\\App\\Controllers\\Jij::updateemail"},{"method":"POST","route":"atl\/data\/aset-tetap-lainnya\/upload","handler":"\\App\\Controllers\\Atl::atlupload"},{"method":"POST","route":"atl\/data\/aset-tetap-lainnya\/detail","handler":"\\App\\Controllers\\Atl::atldetail"},{"method":"POST","route":"atl\/data\/aset-tetap-lainnya\/delete","handler":"\\App\\Controllers\\Atl::atldelete"},{"method":"POST","route":"atl\/account\/update\/password","handler":"\\App\\Controllers\\Atl::updatepassword"},{"method":"POST","route":"atl\/account\/update\/email","handler":"\\App\\Controllers\\Atl::updateemail"},{"method":"POST","route":"kdp\/data\/konstruksi-dalam-pengerjaan\/upload","handler":"\\App\\Controllers\\Kdp::kdpupload"},{"method":"POST","route":"kdp\/data\/konstruksi-dalam-pengerjaan\/detail","handler":"\\App\\Controllers\\Kdp::kdpdetail"},{"method":"POST","route":"kdp\/data\/konstruksi-dalam-pengerjaan\/delete","handler":"\\App\\Controllers\\Kdp::kdpdelete"},{"method":"POST","route":"kdp\/account\/update\/password","handler":"\\App\\Controllers\\Kdp::updatepassword"},{"method":"POST","route":"kdp\/account\/update\/email","handler":"\\App\\Controllers\\Kdp::updateemail"},{"method":"CLI","route":"ci(.*)","handler":"\\CodeIgniter\\CLI\\CommandRunner::index\/$1"}]},"badgeValue":24,"isEmpty":false,"hasTabContent":true,"hasLabel":false,"icon":"data:image\/png;base64,iVBORw0KGgoAAAANSUhEUgAAABgAAAAYCAYAAADgdz34AAAAAXNSR0IArs4c6QAAAARnQU1BAACxjwv8YQUAAAAJcEhZcwAADsMAAA7DAcdvqGQAAAFDSURBVEhL7ZRNSsNQFIUjVXSiOFEcuQIHDpzpxC0IGYeE\/BEInbWlCHEDLsSiuANdhKDjgm6ggtSJ+l25ldrmmTwIgtgDh\/t37r1J+16cX0dRFMtpmu5pWAkrvYjjOB7AETzStBFW+inxu3KUJMmhludQpoflS1zXban4LYqiO224h6VLTHr8Z+z8EpIHFF9gG78nDVmW7UgTHKjsCyY98QP+pcq+g8Ku2s8G8X3f3\/I8b038WZTp+bO38zxfFd+I6YY6sNUvFlSDk9CRhiAI1jX1I9Cfw7GG1UB8LAuwbU0ZwQnbRDeEN5qqBxZMLtE1ti9LtbREnMIuOXnyIf5rGIb7Wq8HmlZgwYBH7ORTcKH5E4mpjeGt9fBZcHE2GCQ3Vt7oTNPNg+FXLHnSsHkw\/FR+Gg2bB8Ptzrst\/v6C\/wrH+QB+duli6MYJdQAAAABJRU5ErkJggg==","hasTimelineData":false,"timelineData":[]},{"title":"Events","titleSafe":"events","titleDetails":"","display":{"events":{"pre_system":{"event":"pre_system","duration":"4.96","count":1},"dbquery":{"event":"dbquery","duration":"0.17","count":3}}},"badgeValue":4,"isEmpty":false,"hasTabContent":true,"hasLabel":false,"icon":"data:image\/png;base64,iVBORw0KGgoAAAANSUhEUgAAABgAAAAYCAYAAADgdz34AAAAAXNSR0IArs4c6QAAAARnQU1BAACxjwv8YQUAAAAJcEhZcwAADsMAAA7DAcdvqGQAAAEASURBVEhL7ZXNDcIwDIVTsRBH1uDQDdquUA6IM1xgCA6MwJUN2hk6AQzAz0vl0ETUxC5VT3zSU5w81\/mRMGZysixbFEVR0jSKNt8geQU9aRpFmp\/keX6AbjZ5oB74vsaN5lSzA4tLSjpBFxsjeSuRy4d2mDdQTWU7YLbXTNN05mKyovj5KL6B7q3hoy3KwdZxBlT+Ipz+jPHrBqOIynZgcZonoukb\/0ckiTHqNvDXtXEAaygRbaB9FvUTjRUHsIYS0QaSp+Dw6wT4hiTmYHOcYZsdLQ2CbXa4ftuuYR4x9vYZgdb4vsFYUdmABMYeukK9\/SUme3KMFQ77+Yfzh8eYF8+orDuDWU5LAAAAAElFTkSuQmCC","hasTimelineData":false,"timelineData":[]}],"vars":{"varData":{"View Data":{"session":"<div class=\"kint-rich\"><dl><dt class=\"kint-parent\"><span class=\"kint-popup-trigger\" title=\"Open in new window\">&boxbox;<\/span><span class=\"kint-search-trigger\" title=\"Show search box\">&telrec;<\/span><input type=\"text\" class=\"kint-search\" value=\"\"><nav><\/nav><dfn>$value<\/dfn> <var>array<\/var> (1)<\/dt><dd><dl><dt class=\"kint-parent\"><span class=\"kint-access-path-trigger\" title=\"Show access path\">&rlarr;<\/span><span class=\"kint-popup-trigger\" title=\"Open in new window\">&boxbox;<\/span><nav><\/nav><dfn>0<\/dfn> =&gt; <var>array<\/var> (8)<div class=\"access-path\">$value[0]<\/div><\/dt><dd><dl><dt><span class=\"kint-access-path-trigger\" title=\"Show access path\">&rlarr;<\/span><dfn>id<\/dfn> =&gt; <var>string<\/var> (1) \"1\"<div class=\"access-path\">$value[0]['id']<\/div><\/dt><\/dl><dl><dt><span class=\"kint-access-path-trigger\" title=\"Show access path\">&rlarr;<\/span><dfn>name<\/dfn> =&gt; <var>string<\/var> (13) \"Administrator\"<div class=\"access-path\">$value[0]['name']<\/div><\/dt><\/dl><dl><dt><span class=\"kint-access-path-trigger\" title=\"Show access path\">&rlarr;<\/span><dfn>email<\/dfn> =&gt; <var>string<\/var> (16) \"admin@edu-bmn.id\"<div class=\"access-path\">$value[0]['email']<\/div><\/dt><\/dl><dl><dt><span class=\"kint-access-path-trigger\" title=\"Show access path\">&rlarr;<\/span><dfn>password<\/dfn> =&gt; <var>string<\/var> (60) \"$2y$10$a7W4sEXFkieOTzD0nz.5f.iFTRWHNyRNApSRDFWCHNpJ\/aMzV6hsq\"<div class=\"access-path\">$value[0]['password']<\/div><\/dt><\/dl><dl><dt><span class=\"kint-access-path-trigger\" title=\"Show access path\">&rlarr;<\/span><dfn>role<\/dfn> =&gt; <var>string<\/var> (5) \"admin\"<div class=\"access-path\">$value[0]['role']<\/div><\/dt><\/dl><dl><dt><span class=\"kint-access-path-trigger\" title=\"Show access path\">&rlarr;<\/span><dfn>created_at<\/dfn> =&gt; <var>string<\/var> (19) \"2022-09-25 15:29:34\"<div class=\"access-path\">$value[0]['created_at']<\/div><\/dt><\/dl><dl><dt><span class=\"kint-access-path-trigger\" title=\"Show access path\">&rlarr;<\/span><dfn>updated_at<\/dfn> =&gt; <var>string<\/var> (19) \"2022-09-26 08:12:50\"<div class=\"access-path\">$value[0]['updated_at']<\/div><\/dt><\/dl><dl><dt><span class=\"kint-access-path-trigger\" title=\"Show access path\">&rlarr;<\/span><dfn>deleted_at<\/dfn> =&gt; <var>null<\/var><div class=\"access-path\">$value[0]['deleted_at']<\/div><\/dt><\/dl><\/dd><\/dl><\/dd><\/dl><\/div>","pdmdata":"<div class=\"kint-rich\"><dl><dt class=\"kint-parent\"><span class=\"kint-popup-trigger\" title=\"Open in new window\">&boxbox;<\/span><span class=\"kint-search-trigger\" title=\"Show search box\">&telrec;<\/span><input type=\"text\" class=\"kint-search\" value=\"\"><nav><\/nav><dfn>$value<\/dfn> <var>array<\/var> (6)<\/dt><dd><ul class=\"kint-tabs\"><li class=\"kint-active-tab\">Table (6)<\/li><li>Contents (6)<\/li><\/ul><ul class=\"kint-tab-contents\"><li class=\"kint-show\"><pre><table><thead><tr><th><\/th><th>id<\/th><th>uid<\/th><th>kode_barang<\/th><th>nup<\/th><th>nama_barang<\/th><th>kuantitas<\/th><th>perolehan<\/th><th>no_sk<\/th><th>tanggal_sk<\/th><th>instansi_sk<\/th><th>sesuai<\/th><th>tidak_sesuai<\/th><th>pihak_lain<\/th><th>keterangan<\/th><th>last_editor<\/th><th>created_at<\/th><th>updated_at<\/th><th>deleted_at<\/th><\/tr><\/thead><tbody><tr><th>0<\/th><td title=\"string (1)\">3<\/td><td title=\"string (11)\">30201010011<\/td><td title=\"string (14)\">3.02.01.01.001<\/td><td title=\"string (1)\">1<\/td><td title=\"string (5)\">Sedan<\/td><td title=\"string (1)\">1<\/td><td title=\"string (15)\"> Rp401.300.000 <\/td><td title=\"string (26)\">55\/KM.6\/WKN.15\/KNL.03\/2017<\/td><td title=\"string (1)\">-<\/td><td title=\"string (1)\">-<\/td><td title=\"string (2)\">Ya<\/td><td title=\"string (1)\">-<\/td><td title=\"string (1)\">-<\/td><td title=\"string (7)\">DP 80 A<\/td><td title=\"string (1)\">1<\/td><td title=\"string (19)\">2022-09-26 09:16:56<\/td><td title=\"string (19)\">2022-09-26 09:16:56<\/td><td title=\"null\"><var>null<\/var><\/td><\/tr><tr><th>1<\/th><td title=\"string (1)\">4<\/td><td title=\"string (11)\">30201010012<\/td><td title=\"string (14)\">3.02.01.01.001<\/td><td title=\"string (1)\">2<\/td><td title=\"string (3)\">SUV<\/td><td title=\"string (1)\">1<\/td><td title=\"string (15)\"> Rp701.300.000 <\/td><td title=\"string (26)\">55\/KM.6\/WKN.15\/KNL.03\/2017<\/td><td title=\"string (1)\">-<\/td><td title=\"string (1)\">-<\/td><td title=\"string (2)\">Ya<\/td><td title=\"string (1)\">-<\/td><td title=\"string (1)\">-<\/td><td title=\"string (9)\">DP 1380 A<\/td><td title=\"string (1)\">1<\/td><td title=\"string (19)\">2022-09-26 09:16:56<\/td><td title=\"string (19)\">2022-09-26 09:16:56<\/td><td title=\"null\"><var>null<\/var><\/td><\/tr><tr><th>2<\/th><td title=\"string (1)\">5<\/td><td title=\"string (11)\">30201010013<\/td><td title=\"string (14)\">3.02.01.01.001<\/td><td title=\"string (1)\">3<\/td><td title=\"string (5)\">Truck<\/td><td title=\"string (1)\">1<\/td><td title=\"string (15)\"> Rp901.300.000 <\/td><td title=\"string (26)\">55\/KM.6\/WKN.15\/KNL.03\/2017<\/td><td title=\"string (1)\">-<\/td><td title=\"string (1)\">-<\/td><td title=\"string (2)\">Ya<\/td><td title=\"string (1)\">-<\/td><td title=\"string (1)\">-<\/td><td title=\"string (9)\">DP 8220 A<\/td><td title=\"string (1)\">1<\/td><td title=\"string (19)\">2022-09-26 09:16:56<\/td><td title=\"string (19)\">2022-09-26 09:16:56<\/td><td title=\"null\"><var>null<\/var><\/td><\/tr><tr><th>3<\/th><td title=\"string (1)\">6<\/td><td title=\"string (11)\">30201010014<\/td><td title=\"string (14)\">3.02.01.01.001<\/td><td title=\"string (1)\">4<\/td><td title=\"string (8)\">Mini Bus<\/td><td title=\"string (1)\">1<\/td><td title=\"string (15)\"> Rp701.300.000 <\/td><td title=\"string (26)\">55\/KM.6\/WKN.15\/KNL.03\/2017<\/td><td title=\"string (1)\">-<\/td><td title=\"string (1)\">-<\/td><td title=\"string (2)\">Ya<\/td><td title=\"string (1)\">-<\/td><td title=\"string (1)\">-<\/td><td title=\"string (9)\">DP 8044 A<\/td><td title=\"string (1)\">1<\/td><td title=\"string (19)\">2022-09-26 09:16:56<\/td><td title=\"string (19)\">2022-09-26 09:16:56<\/td><td title=\"null\"><var>null<\/var><\/td><\/tr><tr><th>4<\/th><td title=\"string (1)\">7<\/td><td title=\"string (11)\">30201010015<\/td><td title=\"string (14)\">3.02.01.01.001<\/td><td title=\"string (1)\">5<\/td><td title=\"string (3)\">Bus<\/td><td title=\"string (1)\">1<\/td><td title=\"string (15)\"> Rp801.300.000 <\/td><td title=\"string (26)\">55\/KM.6\/WKN.15\/KNL.03\/2017<\/td><td title=\"string (1)\">-<\/td><td title=\"string (1)\">-<\/td><td title=\"string (2)\">Ya<\/td><td title=\"string (1)\">-<\/td><td title=\"string (1)\">-<\/td><td title=\"string (9)\">DP 8210 A<\/td><td title=\"string (1)\">1<\/td><td title=\"string (19)\">2022-09-26 09:16:56<\/td><td title=\"string (19)\">2022-09-26 09:16:56<\/td><td title=\"null\"><var>null<\/var><\/td><\/tr><tr><th>5<\/th><td title=\"string (1)\">8<\/td><td title=\"string (11)\">30201010016<\/td><td title=\"string (14)\">3.02.01.01.001<\/td><td title=\"string (1)\">6<\/td><td title=\"string (3)\">Van<\/td><td title=\"string (1)\">1<\/td><td title=\"string (15)\"> Rp301.300.000 <\/td><td title=\"string (26)\">55\/KM.6\/WKN.15\/KNL.03\/2017<\/td><td title=\"string (1)\">-<\/td><td title=\"string (1)\">-<\/td><td title=\"string (2)\">Ya<\/td><td title=\"string (1)\">-<\/td><td title=\"string (1)\">-<\/td><td title=\"string (9)\">DP 8074 A<\/td><td title=\"string (1)\">1<\/td><td title=\"string (19)\">2022-09-26 09:16:56<\/td><td title=\"string (19)\">2022-09-26 09:16:56<\/td><td title=\"null\"><var>null<\/var><\/td><\/tr><\/tbody><\/table><\/pre><\/li><li><dl><dt class=\"kint-parent\"><span class=\"kint-access-path-trigger\" title=\"Show access path\">&rlarr;<\/span><span class=\"kint-popup-trigger\" title=\"Open in new window\">&boxbox;<\/span><nav><\/nav><dfn>0<\/dfn> =&gt; <var>array<\/var> (18)<div class=\"access-path\">$value[0]<\/div><\/dt><dd><dl><dt><span class=\"kint-access-path-trigger\" title=\"Show access path\">&rlarr;<\/span><dfn>id<\/dfn> =&gt; <var>string<\/var> (1) \"3\"<div class=\"access-path\">$value[0]['id']<\/div><\/dt><\/dl><dl><dt><span class=\"kint-access-path-trigger\" title=\"Show access path\">&rlarr;<\/span><dfn>uid<\/dfn> =&gt; <var>string<\/var> (11) \"30201010011\"<div class=\"access-path\">$value[0]['uid']<\/div><\/dt><\/dl><dl><dt><span class=\"kint-access-path-trigger\" title=\"Show access path\">&rlarr;<\/span><dfn>kode_barang<\/dfn> =&gt; <var>string<\/var> (14) \"3.02.01.01.001\"<div class=\"access-path\">$value[0]['kode_barang']<\/div><\/dt><\/dl><dl><dt><span class=\"kint-access-path-trigger\" title=\"Show access path\">&rlarr;<\/span><dfn>nup<\/dfn> =&gt; <var>string<\/var> (1) \"1\"<div class=\"access-path\">$value[0]['nup']<\/div><\/dt><\/dl><dl><dt><span class=\"kint-access-path-trigger\" title=\"Show access path\">&rlarr;<\/span><dfn>nama_barang<\/dfn> =&gt; <var>string<\/var> (5) \"Sedan\"<div class=\"access-path\">$value[0]['nama_barang']<\/div><\/dt><\/dl><dl><dt><span class=\"kint-access-path-trigger\" title=\"Show access path\">&rlarr;<\/span><dfn>kuantitas<\/dfn> =&gt; <var>string<\/var> (1) \"1\"<div class=\"access-path\">$value[0]['kuantitas']<\/div><\/dt><\/dl><dl><dt><span class=\"kint-access-path-trigger\" title=\"Show access path\">&rlarr;<\/span><dfn>perolehan<\/dfn> =&gt; <var>string<\/var> (15) \" Rp401.300.000 \"<div class=\"access-path\">$value[0]['perolehan']<\/div><\/dt><\/dl><dl><dt><span class=\"kint-access-path-trigger\" title=\"Show access path\">&rlarr;<\/span><dfn>no_sk<\/dfn> =&gt; <var>string<\/var> (26) \"55\/KM.6\/WKN.15\/KNL.03\/2017\"<div class=\"access-path\">$value[0]['no_sk']<\/div><\/dt><\/dl><dl><dt><span class=\"kint-access-path-trigger\" title=\"Show access path\">&rlarr;<\/span><dfn>tanggal_sk<\/dfn> =&gt; <var>string<\/var> (1) \"-\"<div class=\"access-path\">$value[0]['tanggal_sk']<\/div><\/dt><\/dl><dl><dt><span class=\"kint-access-path-trigger\" title=\"Show access path\">&rlarr;<\/span><dfn>instansi_sk<\/dfn> =&gt; <var>string<\/var> (1) \"-\"<div class=\"access-path\">$value[0]['instansi_sk']<\/div><\/dt><\/dl><dl><dt><span class=\"kint-access-path-trigger\" title=\"Show access path\">&rlarr;<\/span><dfn>sesuai<\/dfn> =&gt; <var>string<\/var> (2) \"Ya\"<div class=\"access-path\">$value[0]['sesuai']<\/div><\/dt><\/dl><dl><dt><span class=\"kint-access-path-trigger\" title=\"Show access path\">&rlarr;<\/span><dfn>tidak_sesuai<\/dfn> =&gt; <var>string<\/var> (1) \"-\"<div class=\"access-path\">$value[0]['tidak_sesuai']<\/div><\/dt><\/dl><dl><dt><span class=\"kint-access-path-trigger\" title=\"Show access path\">&rlarr;<\/span><dfn>pihak_lain<\/dfn> =&gt; <var>string<\/var> (1) \"-\"<div class=\"access-path\">$value[0]['pihak_lain']<\/div><\/dt><\/dl><dl><dt><span class=\"kint-access-path-trigger\" title=\"Show access path\">&rlarr;<\/span><dfn>keterangan<\/dfn> =&gt; <var>string<\/var> (7) \"DP 80 A\"<div class=\"access-path\">$value[0]['keterangan']<\/div><\/dt><\/dl><dl><dt><span class=\"kint-access-path-trigger\" title=\"Show access path\">&rlarr;<\/span><dfn>last_editor<\/dfn> =&gt; <var>string<\/var> (1) \"1\"<div class=\"access-path\">$value[0]['last_editor']<\/div><\/dt><\/dl><dl><dt><span class=\"kint-access-path-trigger\" title=\"Show access path\">&rlarr;<\/span><dfn>created_at<\/dfn> =&gt; <var>string<\/var> (19) \"2022-09-26 09:16:56\"<div class=\"access-path\">$value[0]['created_at']<\/div><\/dt><\/dl><dl><dt><span class=\"kint-access-path-trigger\" title=\"Show access path\">&rlarr;<\/span><dfn>updated_at<\/dfn> =&gt; <var>string<\/var> (19) \"2022-09-26 09:16:56\"<div class=\"access-path\">$value[0]['updated_at']<\/div><\/dt><\/dl><dl><dt><span class=\"kint-access-path-trigger\" title=\"Show access path\">&rlarr;<\/span><dfn>deleted_at<\/dfn> =&gt; <var>null<\/var><div class=\"access-path\">$value[0]['deleted_at']<\/div><\/dt><\/dl><\/dd><\/dl><dl><dt class=\"kint-parent\"><span class=\"kint-access-path-trigger\" title=\"Show access path\">&rlarr;<\/span><span class=\"kint-popup-trigger\" title=\"Open in new window\">&boxbox;<\/span><nav><\/nav><dfn>1<\/dfn> =&gt; <var>array<\/var> (18)<div class=\"access-path\">$value[1]<\/div><\/dt><dd><dl><dt><span class=\"kint-access-path-trigger\" title=\"Show access path\">&rlarr;<\/span><dfn>id<\/dfn> =&gt; <var>string<\/var> (1) \"4\"<div class=\"access-path\">$value[1]['id']<\/div><\/dt><\/dl><dl><dt><span class=\"kint-access-path-trigger\" title=\"Show access path\">&rlarr;<\/span><dfn>uid<\/dfn> =&gt; <var>string<\/var> (11) \"30201010012\"<div class=\"access-path\">$value[1]['uid']<\/div><\/dt><\/dl><dl><dt><span class=\"kint-access-path-trigger\" title=\"Show access path\">&rlarr;<\/span><dfn>kode_barang<\/dfn> =&gt; <var>string<\/var> (14) \"3.02.01.01.001\"<div class=\"access-path\">$value[1]['kode_barang']<\/div><\/dt><\/dl><dl><dt><span class=\"kint-access-path-trigger\" title=\"Show access path\">&rlarr;<\/span><dfn>nup<\/dfn> =&gt; <var>string<\/var> (1) \"2\"<div class=\"access-path\">$value[1]['nup']<\/div><\/dt><\/dl><dl><dt><span class=\"kint-access-path-trigger\" title=\"Show access path\">&rlarr;<\/span><dfn>nama_barang<\/dfn> =&gt; <var>string<\/var> (3) \"SUV\"<div class=\"access-path\">$value[1]['nama_barang']<\/div><\/dt><\/dl><dl><dt><span class=\"kint-access-path-trigger\" title=\"Show access path\">&rlarr;<\/span><dfn>kuantitas<\/dfn> =&gt; <var>string<\/var> (1) \"1\"<div class=\"access-path\">$value[1]['kuantitas']<\/div><\/dt><\/dl><dl><dt><span class=\"kint-access-path-trigger\" title=\"Show access path\">&rlarr;<\/span><dfn>perolehan<\/dfn> =&gt; <var>string<\/var> (15) \" Rp701.300.000 \"<div class=\"access-path\">$value[1]['perolehan']<\/div><\/dt><\/dl><dl><dt><span class=\"kint-access-path-trigger\" title=\"Show access path\">&rlarr;<\/span><dfn>no_sk<\/dfn> =&gt; <var>string<\/var> (26) \"55\/KM.6\/WKN.15\/KNL.03\/2017\"<div class=\"access-path\">$value[1]['no_sk']<\/div><\/dt><\/dl><dl><dt><span class=\"kint-access-path-trigger\" title=\"Show access path\">&rlarr;<\/span><dfn>tanggal_sk<\/dfn> =&gt; <var>string<\/var> (1) \"-\"<div class=\"access-path\">$value[1]['tanggal_sk']<\/div><\/dt><\/dl><dl><dt><span class=\"kint-access-path-trigger\" title=\"Show access path\">&rlarr;<\/span><dfn>instansi_sk<\/dfn> =&gt; <var>string<\/var> (1) \"-\"<div class=\"access-path\">$value[1]['instansi_sk']<\/div><\/dt><\/dl><dl><dt><span class=\"kint-access-path-trigger\" title=\"Show access path\">&rlarr;<\/span><dfn>sesuai<\/dfn> =&gt; <var>string<\/var> (2) \"Ya\"<div class=\"access-path\">$value[1]['sesuai']<\/div><\/dt><\/dl><dl><dt><span class=\"kint-access-path-trigger\" title=\"Show access path\">&rlarr;<\/span><dfn>tidak_sesuai<\/dfn> =&gt; <var>string<\/var> (1) \"-\"<div class=\"access-path\">$value[1]['tidak_sesuai']<\/div><\/dt><\/dl><dl><dt><span class=\"kint-access-path-trigger\" title=\"Show access path\">&rlarr;<\/span><dfn>pihak_lain<\/dfn> =&gt; <var>string<\/var> (1) \"-\"<div class=\"access-path\">$value[1]['pihak_lain']<\/div><\/dt><\/dl><dl><dt><span class=\"kint-access-path-trigger\" title=\"Show access path\">&rlarr;<\/span><dfn>keterangan<\/dfn> =&gt; <var>string<\/var> (9) \"DP 1380 A\"<div class=\"access-path\">$value[1]['keterangan']<\/div><\/dt><\/dl><dl><dt><span class=\"kint-access-path-trigger\" title=\"Show access path\">&rlarr;<\/span><dfn>last_editor<\/dfn> =&gt; <var>string<\/var> (1) \"1\"<div class=\"access-path\">$value[1]['last_editor']<\/div><\/dt><\/dl><dl><dt><span class=\"kint-access-path-trigger\" title=\"Show access path\">&rlarr;<\/span><dfn>created_at<\/dfn> =&gt; <var>string<\/var> (19) \"2022-09-26 09:16:56\"<div class=\"access-path\">$value[1]['created_at']<\/div><\/dt><\/dl><dl><dt><span class=\"kint-access-path-trigger\" title=\"Show access path\">&rlarr;<\/span><dfn>updated_at<\/dfn> =&gt; <var>string<\/var> (19) \"2022-09-26 09:16:56\"<div class=\"access-path\">$value[1]['updated_at']<\/div><\/dt><\/dl><dl><dt><span class=\"kint-access-path-trigger\" title=\"Show access path\">&rlarr;<\/span><dfn>deleted_at<\/dfn> =&gt; <var>null<\/var><div class=\"access-path\">$value[1]['deleted_at']<\/div><\/dt><\/dl><\/dd><\/dl><dl><dt class=\"kint-parent\"><span class=\"kint-access-path-trigger\" title=\"Show access path\">&rlarr;<\/span><span class=\"kint-popup-trigger\" title=\"Open in new window\">&boxbox;<\/span><nav><\/nav><dfn>2<\/dfn> =&gt; <var>array<\/var> (18)<div class=\"access-path\">$value[2]<\/div><\/dt><dd><dl><dt><span class=\"kint-access-path-trigger\" title=\"Show access path\">&rlarr;<\/span><dfn>id<\/dfn> =&gt; <var>string<\/var> (1) \"5\"<div class=\"access-path\">$value[2]['id']<\/div><\/dt><\/dl><dl><dt><span class=\"kint-access-path-trigger\" title=\"Show access path\">&rlarr;<\/span><dfn>uid<\/dfn> =&gt; <var>string<\/var> (11) \"30201010013\"<div class=\"access-path\">$value[2]['uid']<\/div><\/dt><\/dl><dl><dt><span class=\"kint-access-path-trigger\" title=\"Show access path\">&rlarr;<\/span><dfn>kode_barang<\/dfn> =&gt; <var>string<\/var> (14) \"3.02.01.01.001\"<div class=\"access-path\">$value[2]['kode_barang']<\/div><\/dt><\/dl><dl><dt><span class=\"kint-access-path-trigger\" title=\"Show access path\">&rlarr;<\/span><dfn>nup<\/dfn> =&gt; <var>string<\/var> (1) \"3\"<div class=\"access-path\">$value[2]['nup']<\/div><\/dt><\/dl><dl><dt><span class=\"kint-access-path-trigger\" title=\"Show access path\">&rlarr;<\/span><dfn>nama_barang<\/dfn> =&gt; <var>string<\/var> (5) \"Truck\"<div class=\"access-path\">$value[2]['nama_barang']<\/div><\/dt><\/dl><dl><dt><span class=\"kint-access-path-trigger\" title=\"Show access path\">&rlarr;<\/span><dfn>kuantitas<\/dfn> =&gt; <var>string<\/var> (1) \"1\"<div class=\"access-path\">$value[2]['kuantitas']<\/div><\/dt><\/dl><dl><dt><span class=\"kint-access-path-trigger\" title=\"Show access path\">&rlarr;<\/span><dfn>perolehan<\/dfn> =&gt; <var>string<\/var> (15) \" Rp901.300.000 \"<div class=\"access-path\">$value[2]['perolehan']<\/div><\/dt><\/dl><dl><dt><span class=\"kint-access-path-trigger\" title=\"Show access path\">&rlarr;<\/span><dfn>no_sk<\/dfn> =&gt; <var>string<\/var> (26) \"55\/KM.6\/WKN.15\/KNL.03\/2017\"<div class=\"access-path\">$value[2]['no_sk']<\/div><\/dt><\/dl><dl><dt><span class=\"kint-access-path-trigger\" title=\"Show access path\">&rlarr;<\/span><dfn>tanggal_sk<\/dfn> =&gt; <var>string<\/var> (1) \"-\"<div class=\"access-path\">$value[2]['tanggal_sk']<\/div><\/dt><\/dl><dl><dt><span class=\"kint-access-path-trigger\" title=\"Show access path\">&rlarr;<\/span><dfn>instansi_sk<\/dfn> =&gt; <var>string<\/var> (1) \"-\"<div class=\"access-path\">$value[2]['instansi_sk']<\/div><\/dt><\/dl><dl><dt><span class=\"kint-access-path-trigger\" title=\"Show access path\">&rlarr;<\/span><dfn>sesuai<\/dfn> =&gt; <var>string<\/var> (2) \"Ya\"<div class=\"access-path\">$value[2]['sesuai']<\/div><\/dt><\/dl><dl><dt><span class=\"kint-access-path-trigger\" title=\"Show access path\">&rlarr;<\/span><dfn>tidak_sesuai<\/dfn> =&gt; <var>string<\/var> (1) \"-\"<div class=\"access-path\">$value[2]['tidak_sesuai']<\/div><\/dt><\/dl><dl><dt><span class=\"kint-access-path-trigger\" title=\"Show access path\">&rlarr;<\/span><dfn>pihak_lain<\/dfn> =&gt; <var>string<\/var> (1) \"-\"<div class=\"access-path\">$value[2]['pihak_lain']<\/div><\/dt><\/dl><dl><dt><span class=\"kint-access-path-trigger\" title=\"Show access path\">&rlarr;<\/span><dfn>keterangan<\/dfn> =&gt; <var>string<\/var> (9) \"DP 8220 A\"<div class=\"access-path\">$value[2]['keterangan']<\/div><\/dt><\/dl><dl><dt><span class=\"kint-access-path-trigger\" title=\"Show access path\">&rlarr;<\/span><dfn>last_editor<\/dfn> =&gt; <var>string<\/var> (1) \"1\"<div class=\"access-path\">$value[2]['last_editor']<\/div><\/dt><\/dl><dl><dt><span class=\"kint-access-path-trigger\" title=\"Show access path\">&rlarr;<\/span><dfn>created_at<\/dfn> =&gt; <var>string<\/var> (19) \"2022-09-26 09:16:56\"<div class=\"access-path\">$value[2]['created_at']<\/div><\/dt><\/dl><dl><dt><span class=\"kint-access-path-trigger\" title=\"Show access path\">&rlarr;<\/span><dfn>updated_at<\/dfn> =&gt; <var>string<\/var> (19) \"2022-09-26 09:16:56\"<div class=\"access-path\">$value[2]['updated_at']<\/div><\/dt><\/dl><dl><dt><span class=\"kint-access-path-trigger\" title=\"Show access path\">&rlarr;<\/span><dfn>deleted_at<\/dfn> =&gt; <var>null<\/var><div class=\"access-path\">$value[2]['deleted_at']<\/div><\/dt><\/dl><\/dd><\/dl><dl><dt class=\"kint-parent\"><span class=\"kint-access-path-trigger\" title=\"Show access path\">&rlarr;<\/span><span class=\"kint-popup-trigger\" title=\"Open in new window\">&boxbox;<\/span><nav><\/nav><dfn>3<\/dfn> =&gt; <var>array<\/var> (18)<div class=\"access-path\">$value[3]<\/div><\/dt><dd><dl><dt><span class=\"kint-access-path-trigger\" title=\"Show access path\">&rlarr;<\/span><dfn>id<\/dfn> =&gt; <var>string<\/var> (1) \"6\"<div class=\"access-path\">$value[3]['id']<\/div><\/dt><\/dl><dl><dt><span class=\"kint-access-path-trigger\" title=\"Show access path\">&rlarr;<\/span><dfn>uid<\/dfn> =&gt; <var>string<\/var> (11) \"30201010014\"<div class=\"access-path\">$value[3]['uid']<\/div><\/dt><\/dl><dl><dt><span class=\"kint-access-path-trigger\" title=\"Show access path\">&rlarr;<\/span><dfn>kode_barang<\/dfn> =&gt; <var>string<\/var> (14) \"3.02.01.01.001\"<div class=\"access-path\">$value[3]['kode_barang']<\/div><\/dt><\/dl><dl><dt><span class=\"kint-access-path-trigger\" title=\"Show access path\">&rlarr;<\/span><dfn>nup<\/dfn> =&gt; <var>string<\/var> (1) \"4\"<div class=\"access-path\">$value[3]['nup']<\/div><\/dt><\/dl><dl><dt><span class=\"kint-access-path-trigger\" title=\"Show access path\">&rlarr;<\/span><dfn>nama_barang<\/dfn> =&gt; <var>string<\/var> (8) \"Mini Bus\"<div class=\"access-path\">$value[3]['nama_barang']<\/div><\/dt><\/dl><dl><dt><span class=\"kint-access-path-trigger\" title=\"Show access path\">&rlarr;<\/span><dfn>kuantitas<\/dfn> =&gt; <var>string<\/var> (1) \"1\"<div class=\"access-path\">$value[3]['kuantitas']<\/div><\/dt><\/dl><dl><dt><span class=\"kint-access-path-trigger\" title=\"Show access path\">&rlarr;<\/span><dfn>perolehan<\/dfn> =&gt; <var>string<\/var> (15) \" Rp701.300.000 \"<div class=\"access-path\">$value[3]['perolehan']<\/div><\/dt><\/dl><dl><dt><span class=\"kint-access-path-trigger\" title=\"Show access path\">&rlarr;<\/span><dfn>no_sk<\/dfn> =&gt; <var>string<\/var> (26) \"55\/KM.6\/WKN.15\/KNL.03\/2017\"<div class=\"access-path\">$value[3]['no_sk']<\/div><\/dt><\/dl><dl><dt><span class=\"kint-access-path-trigger\" title=\"Show access path\">&rlarr;<\/span><dfn>tanggal_sk<\/dfn> =&gt; <var>string<\/var> (1) \"-\"<div class=\"access-path\">$value[3]['tanggal_sk']<\/div><\/dt><\/dl><dl><dt><span class=\"kint-access-path-trigger\" title=\"Show access path\">&rlarr;<\/span><dfn>instansi_sk<\/dfn> =&gt; <var>string<\/var> (1) \"-\"<div class=\"access-path\">$value[3]['instansi_sk']<\/div><\/dt><\/dl><dl><dt><span class=\"kint-access-path-trigger\" title=\"Show access path\">&rlarr;<\/span><dfn>sesuai<\/dfn> =&gt; <var>string<\/var> (2) \"Ya\"<div class=\"access-path\">$value[3]['sesuai']<\/div><\/dt><\/dl><dl><dt><span class=\"kint-access-path-trigger\" title=\"Show access path\">&rlarr;<\/span><dfn>tidak_sesuai<\/dfn> =&gt; <var>string<\/var> (1) \"-\"<div class=\"access-path\">$value[3]['tidak_sesuai']<\/div><\/dt><\/dl><dl><dt><span class=\"kint-access-path-trigger\" title=\"Show access path\">&rlarr;<\/span><dfn>pihak_lain<\/dfn> =&gt; <var>string<\/var> (1) \"-\"<div class=\"access-path\">$value[3]['pihak_lain']<\/div><\/dt><\/dl><dl><dt><span class=\"kint-access-path-trigger\" title=\"Show access path\">&rlarr;<\/span><dfn>keterangan<\/dfn> =&gt; <var>string<\/var> (9) \"DP 8044 A\"<div class=\"access-path\">$value[3]['keterangan']<\/div><\/dt><\/dl><dl><dt><span class=\"kint-access-path-trigger\" title=\"Show access path\">&rlarr;<\/span><dfn>last_editor<\/dfn> =&gt; <var>string<\/var> (1) \"1\"<div class=\"access-path\">$value[3]['last_editor']<\/div><\/dt><\/dl><dl><dt><span class=\"kint-access-path-trigger\" title=\"Show access path\">&rlarr;<\/span><dfn>created_at<\/dfn> =&gt; <var>string<\/var> (19) \"2022-09-26 09:16:56\"<div class=\"access-path\">$value[3]['created_at']<\/div><\/dt><\/dl><dl><dt><span class=\"kint-access-path-trigger\" title=\"Show access path\">&rlarr;<\/span><dfn>updated_at<\/dfn> =&gt; <var>string<\/var> (19) \"2022-09-26 09:16:56\"<div class=\"access-path\">$value[3]['updated_at']<\/div><\/dt><\/dl><dl><dt><span class=\"kint-access-path-trigger\" title=\"Show access path\">&rlarr;<\/span><dfn>deleted_at<\/dfn> =&gt; <var>null<\/var><div class=\"access-path\">$value[3]['deleted_at']<\/div><\/dt><\/dl><\/dd><\/dl><dl><dt class=\"kint-parent\"><span class=\"kint-access-path-trigger\" title=\"Show access path\">&rlarr;<\/span><span class=\"kint-popup-trigger\" title=\"Open in new window\">&boxbox;<\/span><nav><\/nav><dfn>4<\/dfn> =&gt; <var>array<\/var> (18)<div class=\"access-path\">$value[4]<\/div><\/dt><dd><dl><dt><span class=\"kint-access-path-trigger\" title=\"Show access path\">&rlarr;<\/span><dfn>id<\/dfn> =&gt; <var>string<\/var> (1) \"7\"<div class=\"access-path\">$value[4]['id']<\/div><\/dt><\/dl><dl><dt><span class=\"kint-access-path-trigger\" title=\"Show access path\">&rlarr;<\/span><dfn>uid<\/dfn> =&gt; <var>string<\/var> (11) \"30201010015\"<div class=\"access-path\">$value[4]['uid']<\/div><\/dt><\/dl><dl><dt><span class=\"kint-access-path-trigger\" title=\"Show access path\">&rlarr;<\/span><dfn>kode_barang<\/dfn> =&gt; <var>string<\/var> (14) \"3.02.01.01.001\"<div class=\"access-path\">$value[4]['kode_barang']<\/div><\/dt><\/dl><dl><dt><span class=\"kint-access-path-trigger\" title=\"Show access path\">&rlarr;<\/span><dfn>nup<\/dfn> =&gt; <var>string<\/var> (1) \"5\"<div class=\"access-path\">$value[4]['nup']<\/div><\/dt><\/dl><dl><dt><span class=\"kint-access-path-trigger\" title=\"Show access path\">&rlarr;<\/span><dfn>nama_barang<\/dfn> =&gt; <var>string<\/var> (3) \"Bus\"<div class=\"access-path\">$value[4]['nama_barang']<\/div><\/dt><\/dl><dl><dt><span class=\"kint-access-path-trigger\" title=\"Show access path\">&rlarr;<\/span><dfn>kuantitas<\/dfn> =&gt; <var>string<\/var> (1) \"1\"<div class=\"access-path\">$value[4]['kuantitas']<\/div><\/dt><\/dl><dl><dt><span class=\"kint-access-path-trigger\" title=\"Show access path\">&rlarr;<\/span><dfn>perolehan<\/dfn> =&gt; <var>string<\/var> (15) \" Rp801.300.000 \"<div class=\"access-path\">$value[4]['perolehan']<\/div><\/dt><\/dl><dl><dt><span class=\"kint-access-path-trigger\" title=\"Show access path\">&rlarr;<\/span><dfn>no_sk<\/dfn> =&gt; <var>string<\/var> (26) \"55\/KM.6\/WKN.15\/KNL.03\/2017\"<div class=\"access-path\">$value[4]['no_sk']<\/div><\/dt><\/dl><dl><dt><span class=\"kint-access-path-trigger\" title=\"Show access path\">&rlarr;<\/span><dfn>tanggal_sk<\/dfn> =&gt; <var>string<\/var> (1) \"-\"<div class=\"access-path\">$value[4]['tanggal_sk']<\/div><\/dt><\/dl><dl><dt><span class=\"kint-access-path-trigger\" title=\"Show access path\">&rlarr;<\/span><dfn>instansi_sk<\/dfn> =&gt; <var>string<\/var> (1) \"-\"<div class=\"access-path\">$value[4]['instansi_sk']<\/div><\/dt><\/dl><dl><dt><span class=\"kint-access-path-trigger\" title=\"Show access path\">&rlarr;<\/span><dfn>sesuai<\/dfn> =&gt; <var>string<\/var> (2) \"Ya\"<div class=\"access-path\">$value[4]['sesuai']<\/div><\/dt><\/dl><dl><dt><span class=\"kint-access-path-trigger\" title=\"Show access path\">&rlarr;<\/span><dfn>tidak_sesuai<\/dfn> =&gt; <var>string<\/var> (1) \"-\"<div class=\"access-path\">$value[4]['tidak_sesuai']<\/div><\/dt><\/dl><dl><dt><span class=\"kint-access-path-trigger\" title=\"Show access path\">&rlarr;<\/span><dfn>pihak_lain<\/dfn> =&gt; <var>string<\/var> (1) \"-\"<div class=\"access-path\">$value[4]['pihak_lain']<\/div><\/dt><\/dl><dl><dt><span class=\"kint-access-path-trigger\" title=\"Show access path\">&rlarr;<\/span><dfn>keterangan<\/dfn> =&gt; <var>string<\/var> (9) \"DP 8210 A\"<div class=\"access-path\">$value[4]['keterangan']<\/div><\/dt><\/dl><dl><dt><span class=\"kint-access-path-trigger\" title=\"Show access path\">&rlarr;<\/span><dfn>last_editor<\/dfn> =&gt; <var>string<\/var> (1) \"1\"<div class=\"access-path\">$value[4]['last_editor']<\/div><\/dt><\/dl><dl><dt><span class=\"kint-access-path-trigger\" title=\"Show access path\">&rlarr;<\/span><dfn>created_at<\/dfn> =&gt; <var>string<\/var> (19) \"2022-09-26 09:16:56\"<div class=\"access-path\">$value[4]['created_at']<\/div><\/dt><\/dl><dl><dt><span class=\"kint-access-path-trigger\" title=\"Show access path\">&rlarr;<\/span><dfn>updated_at<\/dfn> =&gt; <var>string<\/var> (19) \"2022-09-26 09:16:56\"<div class=\"access-path\">$value[4]['updated_at']<\/div><\/dt><\/dl><dl><dt><span class=\"kint-access-path-trigger\" title=\"Show access path\">&rlarr;<\/span><dfn>deleted_at<\/dfn> =&gt; <var>null<\/var><div class=\"access-path\">$value[4]['deleted_at']<\/div><\/dt><\/dl><\/dd><\/dl><dl><dt class=\"kint-parent\"><span class=\"kint-access-path-trigger\" title=\"Show access path\">&rlarr;<\/span><span class=\"kint-popup-trigger\" title=\"Open in new window\">&boxbox;<\/span><nav><\/nav><dfn>5<\/dfn> =&gt; <var>array<\/var> (18)<div class=\"access-path\">$value[5]<\/div><\/dt><dd><dl><dt><span class=\"kint-access-path-trigger\" title=\"Show access path\">&rlarr;<\/span><dfn>id<\/dfn> =&gt; <var>string<\/var> (1) \"8\"<div class=\"access-path\">$value[5]['id']<\/div><\/dt><\/dl><dl><dt><span class=\"kint-access-path-trigger\" title=\"Show access path\">&rlarr;<\/span><dfn>uid<\/dfn> =&gt; <var>string<\/var> (11) \"30201010016\"<div class=\"access-path\">$value[5]['uid']<\/div><\/dt><\/dl><dl><dt><span class=\"kint-access-path-trigger\" title=\"Show access path\">&rlarr;<\/span><dfn>kode_barang<\/dfn> =&gt; <var>string<\/var> (14) \"3.02.01.01.001\"<div class=\"access-path\">$value[5]['kode_barang']<\/div><\/dt><\/dl><dl><dt><span class=\"kint-access-path-trigger\" title=\"Show access path\">&rlarr;<\/span><dfn>nup<\/dfn> =&gt; <var>string<\/var> (1) \"6\"<div class=\"access-path\">$value[5]['nup']<\/div><\/dt><\/dl><dl><dt><span class=\"kint-access-path-trigger\" title=\"Show access path\">&rlarr;<\/span><dfn>nama_barang<\/dfn> =&gt; <var>string<\/var> (3) \"Van\"<div class=\"access-path\">$value[5]['nama_barang']<\/div><\/dt><\/dl><dl><dt><span class=\"kint-access-path-trigger\" title=\"Show access path\">&rlarr;<\/span><dfn>kuantitas<\/dfn> =&gt; <var>string<\/var> (1) \"1\"<div class=\"access-path\">$value[5]['kuantitas']<\/div><\/dt><\/dl><dl><dt><span class=\"kint-access-path-trigger\" title=\"Show access path\">&rlarr;<\/span><dfn>perolehan<\/dfn> =&gt; <var>string<\/var> (15) \" Rp301.300.000 \"<div class=\"access-path\">$value[5]['perolehan']<\/div><\/dt><\/dl><dl><dt><span class=\"kint-access-path-trigger\" title=\"Show access path\">&rlarr;<\/span><dfn>no_sk<\/dfn> =&gt; <var>string<\/var> (26) \"55\/KM.6\/WKN.15\/KNL.03\/2017\"<div class=\"access-path\">$value[5]['no_sk']<\/div><\/dt><\/dl><dl><dt><span class=\"kint-access-path-trigger\" title=\"Show access path\">&rlarr;<\/span><dfn>tanggal_sk<\/dfn> =&gt; <var>string<\/var> (1) \"-\"<div class=\"access-path\">$value[5]['tanggal_sk']<\/div><\/dt><\/dl><dl><dt><span class=\"kint-access-path-trigger\" title=\"Show access path\">&rlarr;<\/span><dfn>instansi_sk<\/dfn> =&gt; <var>string<\/var> (1) \"-\"<div class=\"access-path\">$value[5]['instansi_sk']<\/div><\/dt><\/dl><dl><dt><span class=\"kint-access-path-trigger\" title=\"Show access path\">&rlarr;<\/span><dfn>sesuai<\/dfn> =&gt; <var>string<\/var> (2) \"Ya\"<div class=\"access-path\">$value[5]['sesuai']<\/div><\/dt><\/dl><dl><dt><span class=\"kint-access-path-trigger\" title=\"Show access path\">&rlarr;<\/span><dfn>tidak_sesuai<\/dfn> =&gt; <var>string<\/var> (1) \"-\"<div class=\"access-path\">$value[5]['tidak_sesuai']<\/div><\/dt><\/dl><dl><dt><span class=\"kint-access-path-trigger\" title=\"Show access path\">&rlarr;<\/span><dfn>pihak_lain<\/dfn> =&gt; <var>string<\/var> (1) \"-\"<div class=\"access-path\">$value[5]['pihak_lain']<\/div><\/dt><\/dl><dl><dt><span class=\"kint-access-path-trigger\" title=\"Show access path\">&rlarr;<\/span><dfn>keterangan<\/dfn> =&gt; <var>string<\/var> (9) \"DP 8074 A\"<div class=\"access-path\">$value[5]['keterangan']<\/div><\/dt><\/dl><dl><dt><span class=\"kint-access-path-trigger\" title=\"Show access path\">&rlarr;<\/span><dfn>last_editor<\/dfn> =&gt; <var>string<\/var> (1) \"1\"<div class=\"access-path\">$value[5]['last_editor']<\/div><\/dt><\/dl><dl><dt><span class=\"kint-access-path-trigger\" title=\"Show access path\">&rlarr;<\/span><dfn>created_at<\/dfn> =&gt; <var>string<\/var> (19) \"2022-09-26 09:16:56\"<div class=\"access-path\">$value[5]['created_at']<\/div><\/dt><\/dl><dl><dt><span class=\"kint-access-path-trigger\" title=\"Show access path\">&rlarr;<\/span><dfn>updated_at<\/dfn> =&gt; <var>string<\/var> (19) \"2022-09-26 09:16:56\"<div class=\"access-path\">$value[5]['updated_at']<\/div><\/dt><\/dl><dl><dt><span class=\"kint-access-path-trigger\" title=\"Show access path\">&rlarr;<\/span><dfn>deleted_at<\/dfn> =&gt; <var>null<\/var><div class=\"access-path\">$value[5]['deleted_at']<\/div><\/dt><\/dl><\/dd><\/dl><\/li><\/ul><\/dd><\/dl><\/div>"}},"session":{"__ci_last_regenerate":"<pre>1664161338<\/pre>","_ci_previous_url":"https:\/\/edu-bmn.id\/index.php\/admin\/data\/peralatan-dan-mesin","dbmn_user_session":"admin@edu-bmn.id"},"headers":{"Accept":"text\/html,application\/xhtml+xml,application\/xml;q=0.9,image\/avif,image\/webp,image\/apng,*\/*;q=0.8,application\/signed-exchange;v=b3;q=0.9","Accept-Language":"en-GB,en;q=0.9,id-ID;q=0.8,id;q=0.7,en-US;q=0.6","Connection":"close","Cookie":"debug-bar-state=minimized; ci_session=514d205a1de2c8c70e52a9968e19832faeaf335a","Host":"edu-bmn.id","Referer":"https:\/\/edu-bmn.id\/admin\/user-management","User-Agent":"Mozilla\/5.0 (Macintosh; Intel Mac OS X 10_15_7) AppleWebKit\/537.36 (KHTML, like Gecko) Chrome\/105.0.0.0 Safari\/537.36","Cache-Control":"max-age=0","X-Real-Ip":"2001:448a:7022:1dba:3811:d708:7ba3:769f","X-Forwarded-Host":"edu-bmn.id","X-Forwarded-Server":"edu-bmn.id","X-Forwarded-Proto":"https","X-Forwarded-Port":"443","Sec-Ch-Ua":"&quot;Google Chrome&quot;;v=&quot;105&quot;, &quot;Not)A;Brand&quot;;v=&quot;8&quot;, &quot;Chromium&quot;;v=&quot;105&quot;","Sec-Ch-Ua-Mobile":"?0","Sec-Ch-Ua-Platform":"&quot;macOS&quot;","Upgrade-Insecure-Requests":"1","Sec-Fetch-Site":"same-origin","Sec-Fetch-Mode":"navigate","Sec-Fetch-User":"?1","Sec-Fetch-Dest":"document","Pagespeed":"off"},"cookies":{"debug-bar-state":"minimized","ci_session":"514d205a1de2c8c70e52a9968e19832faeaf335a"},"request":"HTTPS\/1.1","response":{"statusCode":200,"reason":"OK","contentType":"text\/html; charset=UTF-8","headers":{"Cache-control":"no-store, max-age=0, no-cache","Content-Type":"text\/html; charset=UTF-8"}}},"config":{"ciVersion":"4.2.6","phpVersion":"7.4.30","phpSAPI":"litespeed","environment":"development","baseURL":"https:\/\/edu-bmn.id\/","timezone":"Asia\/Jakarta","locale":"id","cspEnabled":false}}